perturbationx/CausalNetwork.py
perturbationx/__init__.py
perturbationx/io/RelationTranslator.py
perturbationx/io/__init__.py
perturbationx/io/network_io.py
perturbationx/resources/__init__.py
perturbationx/resources/default-style.xml
perturbationx/resources/osmotic_stress_boundary.tsv
perturbationx/resources/osmotic_stress_core.tsv
perturbationx/resources/osmotic_stress_dataset_1.tsv
perturbationx/resources/osmotic_stress_dataset_2.tsv
perturbationx/resources/osmotic_stress_dataset_3.tsv
perturbationx/resources/resources.py
perturbationx/result/NPAResult.py
perturbationx/result/NPAResultBuilder.py
perturbationx/result/__init__.py
perturbationx/toponpa/__init__.py
perturbationx/toponpa/core.py
perturbationx/toponpa/matrices.py
perturbationx/toponpa/toponpa.py
perturbationx/toponpa/permutation/__init__.py
perturbationx/toponpa/permutation/adjacency_permutation.py
perturbationx/toponpa/permutation/permutation.py
perturbationx/toponpa/preprocessing/__init__.py
perturbationx/toponpa/preprocessing/preprocess_network.py
perturbationx/toponpa/preprocessing/preprocessing.py
perturbationx/toponpa/statistics/__init__.py
perturbationx/toponpa/statistics/permutation_tests.py
perturbationx/toponpa/statistics/statistics.py
perturbationx/toponpa/statistics/variance.py
perturbationx/util/__init__.py
perturbationx/util/connectivity.py
perturbationx/util/neighbors.py
perturbationx/util/shortest_paths.py
perturbationx/vis/NPAResultDisplay.py
perturbationx/vis/__init__.py
perturbationx/vis/cytoscape.py
perturbationx-1.0.1.dist-info/METADATA
perturbationx-1.0.1.dist-info/WHEEL
perturbationx-1.0.1.dist-info/top_level.txt
perturbationx-1.0.1.dist-info/RECORD
