Metadata-Version: 2.1
Name: perturbationx
Version: 1.0.1
Summary: Python package for computing causal network perturbation
License: CC BY-NC 4.0
Project-URL: documentation, https://mikethenut.github.io/perturbationx/index.html
Project-URL: repository, https://github.com/mikethenut/perturbationx
Requires-Python: >=3.10
Requires-Dist: numpy
Requires-Dist: networkx
Requires-Dist: pandas
Requires-Dist: scipy
Requires-Dist: matplotlib
Requires-Dist: seaborn
Requires-Dist: py4cytoscape
